ec2shrink/__init__.py
ec2shrink/__main__.py
ec2shrink-1.1.0.dist-info/LICENSE
ec2shrink-1.1.0.dist-info/METADATA
ec2shrink-1.1.0.dist-info/WHEEL
ec2shrink-1.1.0.dist-info/entry_points.txt
ec2shrink-1.1.0.dist-info/top_level.txt
ec2shrink-1.1.0.dist-info/RECORD
